AUTHORS
CHANGES
LICENSE
MANIFEST.in
README.rst
setup.cfg
setup.py
docs/Makefile
docs/api.txt
docs/changes.txt
docs/conf.py
docs/development.txt
docs/index.txt
docs/installation.txt
docs/license.txt
docs/quickstart.txt
docxgen/__init__.py
docxgen.egg-info/PKG-INFO
docxgen.egg-info/SOURCES.txt
docxgen.egg-info/dependency_links.txt
docxgen.egg-info/requires.txt
docxgen.egg-info/top_level.txt
docxgen/templates/[Content_Types].xml
docxgen/templates/_rels/.rels
docxgen/templates/docProps/app.xml
docxgen/templates/word/document.xml
docxgen/templates/word/fontTable.xml
docxgen/templates/word/numbering.xml
docxgen/templates/word/settings.xml
docxgen/templates/word/styles.xml
docxgen/templates/word/stylesWithEffects.xml
docxgen/templates/word/webSettings.xml
docxgen/templates/word/_rels/document.xml.rels
docxgen/templates/word/theme/theme1.xml
tests/__init__.py
tests/test_docx.py
tests/test_wordml.py