Metadata-Version: 1.0
Name: docxgen
Version: 0.1.4
Summary: A library to generate Microsoft Office Word 2007 documents.
Home-page: http://github.com/kunxi/docxgen
Author: Kun Xi
Author-email: kunxi@kunxi.org
License: MIT
Platform: UNKNOWN
